se_bot_checker/__init__.py
se_bot_checker/bots.py
se_bot_checker-1.0.3.dist-info/LICENSE
se_bot_checker-1.0.3.dist-info/METADATA
se_bot_checker-1.0.3.dist-info/WHEEL
se_bot_checker-1.0.3.dist-info/top_level.txt
se_bot_checker-1.0.3.dist-info/RECORD
