Metadata-Version: 2.1
Name: se-bot-checker
Version: 1.0.3
Summary: This is a python library that verifies the validity of a search engine crawler.
Home-page: https://github.com/danielmorell/se_bot_checker
Author: Daniel Morell
Author-email: office@carintek.com
License: GPLv3+
Project-URL: Source Code, https://github.com/danielmorell/se_bot_checker
Project-URL: Issue tracker, https://github.com/danielmorell/se_bot_checker/issues
Platform: UNKNOWN
Classifier: Development Status :: 5 - Production/Stable
Classifier: Intended Audience :: Developers
Classifier: Intended Audience :: System Administrators
Classifier: Intended Audience :: Information Technology
Classifier: License :: OSI Approved :: GNU General Public License v3 or later (GPLv3+)
Classifier: Operating System :: OS Independent
Classifier: Programming Language :: Python
Classifier: Programming Language :: Python :: 3
Classifier: Programming Language :: Python :: 3.6
Classifier: Programming Language :: Python :: 3.7
Classifier: Programming Language :: Python :: 3.8
Requires-Python: >=3.6
License-File: LICENSE
